pyleetup/__init__.py
pyleetup/display_question.py
pyleetup/main.py
pyleetup/run_solution.py
pyleetup/solve.py
pyleetup/queries/__init__.py
pyleetup/queries/fetch_question.py
pyleetup/queries/fetch_snippets.py
pyleetup/queries/fetch_stats.py
pyleetup/queries/judge.py
pyleetup/queries/status.py
pyleetup-0.0.2.dist-info/METADATA
pyleetup-0.0.2.dist-info/WHEEL
pyleetup-0.0.2.dist-info/entry_points.txt
pyleetup-0.0.2.dist-info/RECORD
